modular2d/__init__.py
modular2d/border.py
modular2d/modulate.py
modular2d-1.0a1.dist-info/licenses/LICENCE
modular2d-1.0a1.dist-info/METADATA
modular2d-1.0a1.dist-info/WHEEL
modular2d-1.0a1.dist-info/top_level.txt
modular2d-1.0a1.dist-info/RECORD
