Metadata-Version: 2.4
Name: modular2d
Version: 1.0a1
Author: moduLab7
License: MIT
Project-URL: Repository, https://github.com/moduLab7/Modular2d
Requires-Python: >=3.7
License-File: LICENCE
Dynamic: license-file
